setup.cfg
setup.py
waydame/__init__.py
waydame/job.py
waydame.egg-info/PKG-INFO
waydame.egg-info/SOURCES.txt
waydame.egg-info/dependency_links.txt
waydame.egg-info/not-zip-safe
waydame.egg-info/requires.txt
waydame.egg-info/top_level.txt
waydame/mobile/__init__.py
waydame/mobile/mobile.py
waydame/net/__init__.py
waydame/net/protocol.py
waydame/web/__init__.py
waydame/web/application.py
waydame/web/defaulthandler.py
waydame/web/requesthandler.py
waydame/web/routes.py