Metadata-Version: 1.0
Name: waydame
Version: 1.0.0.0
Summary: waydame's python library
Home-page: http://waydame.me/
Author: waydame
Author-email: waydame@gmail.com
License: GPL
Keywords: waydame
Platform: any
